ami_supernemo
setup.py
pyAMI_supernemo/__init__.py
pyAMI_supernemo/config.py
pyAMI_supernemo.egg-info/PKG-INFO
pyAMI_supernemo.egg-info/SOURCES.txt
pyAMI_supernemo.egg-info/dependency_links.txt
pyAMI_supernemo.egg-info/not-zip-safe
pyAMI_supernemo.egg-info/requires.txt
pyAMI_supernemo.egg-info/top_level.txt