Metadata-Version: 1.0
Name: pyAMI-supernemo
Version: 5.0.5.999
Summary: Python ATLAS Metadata Interface (pyAMI) for SuperNemo
Home-page: http://ami.in2p3.fr/
Author: Jerome Odier
Author-email: jerome.odier@cern.ch
License: CeCILL-C
Platform: any
